xpay/__init__.py
xpay/client.py
xpay/exceptions.py
xpay/http_client.py
xpay/models/__init__.py
xpay/resources/__init__.py
xpay/resources/customers.py
xpay/resources/payments.py
xpay/resources/webhooks.py
xpay/types/config.py
xpay/utils/__init__.py
xpay/utils/currency.py
xpay/utils/webhook.py
xpay_python_sdk-1.0.0.dist-info/METADATA
xpay_python_sdk-1.0.0.dist-info/WHEEL
xpay_python_sdk-1.0.0.dist-info/RECORD
